CHANGES.txt
LICENSE.txt
MANIFEST.in
README.txt
setup.py
js/__init__.py
js.jquery_json.egg-info/PKG-INFO
js.jquery_json.egg-info/SOURCES.txt
js.jquery_json.egg-info/dependency_links.txt
js.jquery_json.egg-info/entry_points.txt
js.jquery_json.egg-info/namespace_packages.txt
js.jquery_json.egg-info/not-zip-safe
js.jquery_json.egg-info/requires.txt
js.jquery_json.egg-info/top_level.txt
js/jquery_json/__init__.py
js/jquery_json/test_jquery-json.txt
js/jquery_json/resources/jquery.json.js
js/jquery_json/resources/jquery.json.min.js