Metadata-Version: 1.0
Name: js.jquery-json
Version: 2.3
Summary: Fanstatic packaging of jquery-json
Home-page: https://bitbucket.org/fanstatic/js.jquery_json
Author: Fanstatic Developers
Author-email: fanstatic@googlegroups.com
License: BSD
Platform: UNKNOWN
